lib/Logger.py
lib/Service.py
lib/__init__.py
lib/main.py
lib/DataAccess/Neo4jOpr.py
lib/DataAccess/__init__.py
lib/Domain/Controller.py
lib/Domain/Extractor.py
lib/Domain/QueryBuilder.py
lib/Domain/Repository.py
lib/Domain/__init__.py
lib/Presentation/Gate.py
lib/Presentation/__init__.py
lib/Presentation/pres.py
Cypher_Pilot-1.0.0.dist-info/METADATA
Cypher_Pilot-1.0.0.dist-info/WHEEL
Cypher_Pilot-1.0.0.dist-info/top_level.txt
Cypher_Pilot-1.0.0.dist-info/RECORD
